launchlab_django_utils/__init__.py
launchlab_django_utils/context_processors.py
launchlab_django_utils/middleware.py
launchlab_django_utils/models.py
launchlab_django_utils/storage.py
launchlab_django_utils/urls.py
launchlab_django_utils/views.py
launchlab_django_utils/formatters/__init__.py
launchlab_django_utils/formatters/currency.py
launchlab_django_utils/management/__init__.py
launchlab_django_utils/management/commands/__init__.py
launchlab_django_utils/management/commands/create_superuser_and_email_password.py
launchlab_django_utils/static/css/launchlab_django_utils.css
launchlab_django_utils/static/js/launchlab_django_utils.js
launchlab_django_utils/templates/launchlab_django_utils/base.html
launchlab_django_utils-0.9.0.dist-info/METADATA
launchlab_django_utils-0.9.0.dist-info/RECORD
launchlab_django_utils-0.9.0.dist-info/WHEEL
launchlab_django_utils-0.9.0.dist-info/top_level.txt
