Metadata-Version: 2.1
Name: launchlab-django-utils
Version: 0.9.0
Summary: Useful bits and pieces for Django projects.
Home-page: https://github.com/LaunchlabAU/launchlab-django-utils
Author: Dave Pretty
Author-email: david@launchlab.com.au
License: MIT
Keywords: launchlab-django-utils
Platform: UNKNOWN
Classifier: Development Status :: 3 - Alpha
Classifier: Framework :: Django
Classifier: Framework :: Django :: 1.8
Classifier: Framework :: Django :: 1.9
Classifier: Framework :: Django :: 1.10
Classifier: Framework :: Django :: 1.11
Classifier: Intended Audience :: Developers
Classifier: License :: OSI Approved :: BSD License
Classifier: Natural Language :: English
Classifier: Programming Language :: Python :: 2
Classifier: Programming Language :: Python :: 2.7
Classifier: Programming Language :: Python :: 3
Classifier: Programming Language :: Python :: 3.4
Classifier: Programming Language :: Python :: 3.5
Classifier: Programming Language :: Python :: 3.6
